client3x/AsyncClient.py
client3x/Client.py
client3x/ClientPayload.py
client3x/InboundPayload.py
client3x/PanelResponse.py
client3x/__init__.py
client3x/errors.py
client3x/payload.py
docs/Documentation.md
examples/Client_methods_example.py
examples/__init__.py
examples/config.py
examples/example_Async_Client_usage.py
examples/example_Client_usage.py
examples/example_config.py
examples/__pycache__/__init__.cpython-312.pyc
examples/__pycache__/example_config.cpython-312.pyc
examples/payloads_example/client_payload_example.py
examples/payloads_example/custom_payload_class_example.py
examples/payloads_example/inbound_payload_example.py
client3x-1.2.1.dist-info/LICENSE
client3x-1.2.1.dist-info/METADATA
client3x-1.2.1.dist-info/WHEEL
client3x-1.2.1.dist-info/top_level.txt
client3x-1.2.1.dist-info/RECORD
