Metadata-Version: 2.2
Name: client3x
Version: 1.2.1
Summary: A python Client for 3X-UI client
Home-page: https://github.com/wert-rar/ThreeX-Python-Client.git
Author: Wert-Rar
Author-email: Wert-Rar <wert-rar@mail.ru>
License: MIT
Project-URL: Homepage, https://github.com/wert-rar/ThreeX-Python-Client.git
Project-URL: Repository, https://github.com/wert-rar/ThreeX-Python-Client.git
Requires-Python: >=3.10
License-File: LICENSE
Requires-Dist: aiohttp>=3.11.11
Requires-Dist: requests>=2.32.3
Dynamic: author
Dynamic: home-page
Dynamic: requires-python
